pktype/__init__.py
pktype/pokemon_type.py
pktype/type_file.py
pktype-0.0.1.post2302071248.dist-info/METADATA
pktype-0.0.1.post2302071248.dist-info/WHEEL
pktype-0.0.1.post2302071248.dist-info/top_level.txt
pktype-0.0.1.post2302071248.dist-info/zip-safe
pktype-0.0.1.post2302071248.dist-info/RECORD
